intervalgenerator
