Metadata-Version: 1.1
Name: python-date-interval-generator
Version: 0.0.2
Summary: Generates common sequential date intervals for a given date range
Home-page: https://github.com/nutso/python-date-interval-generator
Author: @nutso
Author-email: nutsoapps@gmail.com
License: UNKNOWN
Keywords: date interval dateutil
Platform: UNKNOWN
Classifier: Development Status :: 3 - Alpha
Classifier: Programming Language :: Python :: 2.7
Classifier: Programming Language :: Python :: 3.5
